kinto2xml/__init__.py
kinto2xml/amo.py
kinto2xml/compare.py
kinto2xml/constants.py
kinto2xml/exporter.py
kinto2xml/importer.py
kinto2xml/kinto.py
kinto2xml/logger.py
kinto2xml/synchronize.py
kinto2xml/verifier.py
kinto2xml/tests/__init__.py
kinto2xml/tests/test_amo.py
kinto2xml/tests/test_compare.py
kinto2xml/tests/test_exporter.py
kinto2xml/tests/test_importer.py
kinto2xml/tests/test_kinto.py
kinto2xml/tests/test_synchronize.py
kinto2xml/tests/test_verifier.py
kinto2xml-0.1.0.dist-info/DESCRIPTION.rst
kinto2xml-0.1.0.dist-info/METADATA
kinto2xml-0.1.0.dist-info/RECORD
kinto2xml-0.1.0.dist-info/WHEEL
kinto2xml-0.1.0.dist-info/entry_points.txt
kinto2xml-0.1.0.dist-info/metadata.json
kinto2xml-0.1.0.dist-info/top_level.txt
