Metadata-Version: 2.0
Name: kinto2xml
Version: 0.1.0
Summary: Generate a blocklists.xml file from the Kinto collections.
Home-page: https://github.com/mozilla-services/kinto2xml
Author: Mozilla Services
Author-email: services-dev@mozilla.com
License: Apache License (2.0)
Keywords: web services
Platform: UNKNOWN
Classifier: Programming Language :: Python
Classifier: Programming Language :: Python :: 2
Classifier: Programming Language :: Python :: 2.7
Classifier: Programming Language :: Python :: 3
Classifier: Programming Language :: Python :: 3.4
Classifier: License :: OSI Approved :: Apache Software License
Requires-Dist: kinto-client
Requires-Dist: lxml
Requires-Dist: ndg-httpsclient
Requires-Dist: pyasn1
Requires-Dist: pyopenssl
Requires-Dist: requests
Requires-Dist: six
Requires-Dist: xmltodict
